{
  "helltide": {
    "endTime": "2026-04-27T11:55:00.000Z",
    "id": 1777287600,
    "startTime": "2026-04-27T11:00:00.000Z",
    "zone": "kehjistan",
    "chests": [
      "Scorching Dunes (SW)",
      "Amber Sands",
      "Forgotten Coastline"
    ]
  },
  "world_boss": {
    "boss": "Avarice",
    "id": 1777291200,
    "nextTime": "2026-04-27T15:30:00.000Z",
    "startTime": "2026-04-27T12:00:00.000Z",
    "zone": [
      {
        "boss": "Avarice",
        "id": "kehjistan",
        "isWhisper": false,
        "name": "Kehjistan"
      },
      {
        "boss": "Avarice",
        "id": "nahantu",
        "isWhisper": false,
        "name": "Nahantu"
      }
    ]
  },
  "legion": {
    "id": 1777289700,
    "nextTime": "2026-04-27T12:00:00.000Z",
    "startTime": "2026-04-27T11:35:00.000Z",
    "zoneWindow": true
  },
  "upcoming": {
    "world_boss": [
      {
        "boss": "Avarice",
        "startTime": "2026-04-27T12:00:00.000Z",
        "zone": [
          {
            "id": "kehjistan",
            "name": "Kehjistan",
            "isWhisper": false,
            "boss": "Avarice"
          }
        ]
      },
      {
        "boss": "Avarice",
        "startTime": "2026-04-27T15:30:00.000Z",
        "zone": [
          {
            "id": "scosglen",
            "name": "Scosglen",
            "isWhisper": false,
            "boss": "Avarice"
          }
        ]
      },
      {
        "boss": "Avarice",
        "startTime": "2026-04-27T19:00:00.000Z",
        "zone": [
          {
            "id": "kehjistan",
            "name": "Kehjistan",
            "isWhisper": false,
            "boss": "Avarice"
          },
          {
            "id": "nahantu",
            "name": "Nahantu",
            "isWhisper": false,
            "boss": "Wandering Death"
          }
        ]
      }
    ],
    "helltide": [
      {
        "startTime": "2026-04-27T12:00:00.000Z"
      },
      {
        "startTime": "2026-04-27T13:00:00.000Z"
      },
      {
        "startTime": "2026-04-27T14:00:00.000Z"
      }
    ],
    "legion": [
      {
        "startTime": "2026-04-27T11:35:00.000Z"
      },
      {
        "startTime": "2026-04-27T12:00:00.000Z"
      },
      {
        "startTime": "2026-04-27T12:25:00.000Z"
      }
    ]
  },
  "fetchedAt": "2026-04-27T11:27:02.356Z"
}