{
  "helltide": {
    "endTime": "2026-04-04T16:55:00.000Z",
    "id": 1775318400,
    "startTime": "2026-04-04T16:00:00.000Z",
    "zone": "kehjistan",
    "chests": [
      "Forgotten Coastline (S)",
      "Amber Sands",
      "Scorching Dunes (E)"
    ]
  },
  "world_boss": {
    "boss": "Avarice",
    "id": 1775325600,
    "nextTime": "2026-04-04T21:30:00.000Z",
    "startTime": "2026-04-04T18:00:00.000Z",
    "zone": [
      {
        "boss": "Avarice",
        "id": "dry_steppes",
        "isWhisper": false,
        "name": "Dry Steppes"
      },
      {
        "boss": "Avarice",
        "id": "nahantu",
        "isWhisper": false,
        "name": "Nahantu"
      }
    ]
  },
  "legion": {
    "id": 1775320200,
    "nextTime": "2026-04-04T16:55:00.000Z",
    "startTime": "2026-04-04T16:30:00.000Z"
  },
  "upcoming": {
    "world_boss": [
      {
        "boss": "Avarice",
        "startTime": "2026-04-04T18:00:00.000Z",
        "zone": [
          {
            "id": "dry_steppes",
            "name": "Dry Steppes",
            "isWhisper": false,
            "boss": "Avarice"
          }
        ]
      },
      {
        "boss": "Ashava",
        "startTime": "2026-04-04T21:30:00.000Z",
        "zone": [
          {
            "id": "fractured_peaks",
            "name": "Fractured Peaks",
            "isWhisper": false,
            "boss": "Ashava"
          }
        ]
      },
      {
        "boss": "Ashava",
        "startTime": "2026-04-05T01:00:00.000Z",
        "zone": [
          {
            "id": "dry_steppes",
            "name": "Dry Steppes",
            "isWhisper": false,
            "boss": "Ashava"
          },
          {
            "id": "nahantu",
            "name": "Nahantu",
            "isWhisper": false,
            "boss": "Avarice"
          }
        ]
      }
    ],
    "helltide": [
      {
        "startTime": "2026-04-04T17:00:00.000Z"
      },
      {
        "startTime": "2026-04-04T18:00:00.000Z"
      },
      {
        "startTime": "2026-04-04T19:00:00.000Z"
      }
    ],
    "legion": [
      {
        "startTime": "2026-04-04T16:30:00.000Z"
      },
      {
        "startTime": "2026-04-04T16:55:00.000Z"
      },
      {
        "startTime": "2026-04-04T17:20:00.000Z"
      }
    ]
  },
  "fetchedAt": "2026-04-04T16:14:53.100Z"
}