{
  "helltide": {
    "endTime": "2026-05-24T16:55:00.000Z",
    "id": 1779638400,
    "startTime": "2026-05-24T16:00:00.000Z",
    "zone": "fractured_peaks",
    "chests": [
      "Western Ways",
      "Kor Rohavan"
    ]
  },
  "world_boss": {
    "boss": "Azmodan",
    "id": 1779647400,
    "nextTime": "2026-05-24T22:00:00.000Z",
    "startTime": "2026-05-24T18:30:00.000Z",
    "zone": [
      {
        "boss": "Azmodan",
        "id": "fractured_peaks",
        "isWhisper": false,
        "name": "Fractured Peaks"
      },
      {
        "boss": "Azmodan",
        "id": "scosglen",
        "isWhisper": false,
        "name": "Scosglen"
      }
    ]
  },
  "legion": {
    "id": 1779641700,
    "nextTime": "2026-05-24T17:20:00.000Z",
    "startTime": "2026-05-24T16:55:00.000Z",
    "zoneWindow": true
  },
  "upcoming": {
    "world_boss": [
      {
        "boss": "Azmodan",
        "startTime": "2026-05-24T18:30:00.000Z",
        "zone": [
          {
            "boss": "Azmodan",
            "id": "fractured_peaks",
            "isWhisper": false,
            "name": "Fractured Peaks"
          }
        ]
      },
      {
        "boss": "Wandering Death",
        "startTime": "2026-05-24T22:00:00.000Z",
        "zone": [
          {
            "isWhisper": false,
            "name": "Dry Steppes",
            "id": "dry_steppes",
            "boss": "Wandering Death"
          }
        ]
      },
      {
        "boss": "Wandering Death",
        "startTime": "2026-05-25T01:30:00.000Z",
        "zone": [
          {
            "id": "fractured_peaks",
            "isWhisper": false,
            "name": "Fractured Peaks",
            "boss": "Wandering Death"
          }
        ]
      }
    ],
    "helltide": [
      {
        "startTime": "2026-05-24T17:00:00.000Z"
      },
      {
        "startTime": "2026-05-24T18:00:00.000Z"
      },
      {
        "startTime": "2026-05-24T19:00:00.000Z"
      }
    ],
    "legion": [
      {
        "startTime": "2026-05-24T16:55:00.000Z"
      },
      {
        "startTime": "2026-05-24T17:20:00.000Z"
      },
      {
        "startTime": "2026-05-24T17:45:00.000Z"
      }
    ]
  },
  "fetchedAt": "2026-05-24T16:52:51.512Z"
}